akande/__init__.py
akande/__main__.py
akande/akande.py
akande/cache.py
akande/config.py
akande/logger.py
akande/services.py
akande/utils.py
akande/providers/__init__.py
akande/providers/_openai_compat.py
akande/providers/anthropic_provider.py
akande/providers/azure_openai_provider.py
akande/providers/base.py
akande/providers/cohere_provider.py
akande/providers/google_provider.py
akande/providers/groq_provider.py
akande/providers/huggingface_provider.py
akande/providers/lmstudio_provider.py
akande/providers/mistral_provider.py
akande/providers/ollama_provider.py
akande/providers/openai_provider.py
akande/providers/registry.py
akande/providers/response.py
akande/server/__init__.py
akande/server/server.py
akande-0.0.5.dist-info/licenses/LICENSE-APACHE
akande-0.0.5.dist-info/licenses/LICENSE-MIT
akande-0.0.5.dist-info/METADATA
akande-0.0.5.dist-info/WHEEL
akande-0.0.5.dist-info/entry_points.txt
akande-0.0.5.dist-info/top_level.txt
akande-0.0.5.dist-info/RECORD
