Metadata-Version: 2.4
Name: akande
Version: 0.0.5
Summary: A self-hosted, provider-agnostic voice assistant that delivers structured executive briefings via voice or text from 10 LLM providers.
Author-email: Sebastien Rousseau <sebastian.rousseau@gmail.com>
License: Apache Software License
Project-URL: Homepage, https://akande.co
Project-URL: Repository, https://github.com/sebastienrousseau/akande
Classifier: Development Status :: 4 - Beta
Classifier: Intended Audience :: Developers
Classifier: License :: OSI Approved :: Apache Software License
Classifier: Operating System :: OS Independent
Classifier: Programming Language :: Python :: 3
Classifier: Programming Language :: Python :: 3.9
Classifier: Programming Language :: Python :: 3.10
Classifier: Programming Language :: Python :: 3.11
Classifier: Programming Language :: Python :: 3.12
Requires-Python: >=3.9
License-File: LICENSE-APACHE
License-File: LICENSE-MIT
Requires-Dist: openai>=1.12.0
Requires-Dist: pyaudio>=0.2.14
Requires-Dist: python-dotenv>=1.0.1
Requires-Dist: pyttsx4>=3.0.15
Requires-Dist: reportlab>=4.1.0
Requires-Dist: speechrecognition>=3.10.1
Requires-Dist: cherrypy>=18.8.0
Requires-Dist: pydub>=0.25.1
Provides-Extra: anthropic
Requires-Dist: anthropic>=0.18.0; extra == "anthropic"
Provides-Extra: google
Requires-Dist: google-generativeai>=0.4.0; extra == "google"
Provides-Extra: mistral
Requires-Dist: mistralai>=0.1.0; extra == "mistral"
Provides-Extra: cohere
Requires-Dist: cohere>=5.0.0; extra == "cohere"
Provides-Extra: huggingface
Requires-Dist: huggingface_hub>=0.20.0; extra == "huggingface"
Provides-Extra: all
Requires-Dist: anthropic>=0.18.0; extra == "all"
Requires-Dist: google-generativeai>=0.4.0; extra == "all"
Requires-Dist: mistralai>=0.1.0; extra == "all"
Requires-Dist: cohere>=5.0.0; extra == "all"
Requires-Dist: huggingface_hub>=0.20.0; extra == "all"
Dynamic: license-file
